prolog/__init__.py
prolog/builtins.py
prolog/errors.py
prolog/expression.py
prolog/interpreter.py
prolog/logic_interpreter.py
prolog/math_interpreter.py
prolog/merge_bindings.py
prolog/parser.py
prolog/prolog.py
prolog/repl.py
prolog/scanner.py
prolog/token.py
prolog/token_type.py
prolog/types.py
tests/__init__.py
tests/test_interpreter.py
tests/test_list.py
tests/test_predicate_functions.py
tests/test_scanner.py
pieprolog-1.0.0.dist-info/LICENSE
pieprolog-1.0.0.dist-info/METADATA
pieprolog-1.0.0.dist-info/WHEEL
pieprolog-1.0.0.dist-info/top_level.txt
pieprolog-1.0.0.dist-info/RECORD
