Metadata-Version: 2.1
Name: pieprolog
Version: 1.0.0
Summary: Prolog implemented in Python
Home-page: https://github.com/robjsliwa/pyprolog
Author: Rob Sliwa
Author-email: robjsliwa@example.com
Classifier: Programming Language :: Python :: 3
Classifier: License :: OSI Approved :: MIT License
Classifier: Operating System :: OS Independent
Requires-Python: >=3.10
License-File: LICENSE
Requires-Dist: colorama
Requires-Dist: prompt-toolkit
